cconf/__init__.py
cconf/base.py
cconf/cacheurl.py
cconf/ciphers.py
cconf/cli.py
cconf/contrib/__init__.py
cconf/contrib/secretserver.py
cconf/dburl.py
cconf/exceptions.py
cconf/management/__init__.py
cconf/management/commands/__init__.py
cconf/management/commands/config.py
cconf/policy.py
cconf/py.typed
cconf/sources.py
cconf/types.py
cconf-1.0.0.dist-info/WHEEL
cconf-1.0.0.dist-info/entry_points.txt
cconf-1.0.0.dist-info/METADATA
cconf-1.0.0.dist-info/RECORD
