Metadata-Version: 2.3
Name: cconf
Version: 1.0.0
Summary: Multi-sourced (and optionally encrypted) configuration management.
Author: Dan Watson
Author-email: Dan Watson <watsond@imsweb.com>
License: BSD
Classifier: Intended Audience :: Developers
Classifier: License :: OSI Approved :: BSD License
Classifier: Operating System :: OS Independent
Classifier: Programming Language :: Python
Classifier: Programming Language :: Python :: 3
Requires-Dist: cryptography
Requires-Dist: python-tss-sdk ; extra == 'all'
Requires-Dist: python-tss-sdk ; extra == 'secretserver'
Requires-Python: >=3.10
Project-URL: Homepage, https://github.com/imsweb/cconf
Provides-Extra: all
Provides-Extra: secretserver
